[{"description": "The Last Sync time/date is incorrectly recording the last time the user pressed the sync button; this should be the last API pull\n"}, {"description": "Unknown items and \"Imported by *\" items should always sort after items with valid values\n"}, {"description": "Correct issue with readme date inconsistencies\n"}, {"description": "**Filter Chips Initial Styling Bug** - Chips display wrong styling on page load, correct after filter interaction (BUG-006)\n"}, {"description": "Fuzzy search filter shows American Gold Eagle when typing \"Eagle\" or \"Silver Eagle\" - needs refinement\n"}, {"description": "Error recovery procedures missing for critical failures\n"}, {"description": "Data corruption detection and recovery mechanisms\n"}, {"description": "Agent coordination timeout mechanisms\n"}, {"description": "Memory leak detection for long-running sessions\n"}, {"description": "Cross-browser compatibility edge cases\n"}, {"description": "localStorage quota limit handling\n"}, {"description": "When importing data, if no value is present, check other Numista price values. If none, set the price to 0.00\n"}, {"description": "When opening Numista links, open them in a new, appropriately sized window with close, back, and forward controls\n"}, {"description": "\"Change Log\" should have a square recycle bin icon instead of text\n"}, {"description": "In the table, when filtered, dynamically remove empty columns\n"}, {"description": "When the width narrows to mobile sizes, double the height of the table rows\n"}, {"description": "Re-theme the light mode with the new \"Darker Light\" palette\n"}, {"description": "Add exponential backoff and a user-visible retry banner for API rate limits\n"}, {"description": "Move the \"Minimum Chip Items\" dropdown under the \"Items\" dropdown\n"}, {"description": "Add a checkbox under the \"Minimum Chip Items\" dropdown to include date and price values for all cells\n"}, {"description": "Add a toggle to enable/disable weight in the filters tool\n"}, {"description": "Provide a toggle to switch between a condensed, scrolling view and an auto-expanding view\n"}, {"description": "Group all control toggles into a card under the \"Items\" dropdown\n"}, {"description": "The \"Title/Name\" column should allow fractions\n"}, {"description": "Center the titles and subtitles on the cards in the files modal\n"}, {"description": "Add \"You may be entitled to compensation\" to the boating accident joke, scaled to fit under the button\n"}, {"description": "Add \"Purchase\" and \"Issue\" year filters\n"}, {"description": "Performance monitoring and baseline measurements\n"}, {"description": "Integration testing framework for multi-agent workflows\n"}, {"description": "Automated testing for localStorage quota limits\n"}, {"description": "Security audit automation and scheduling\n"}, {"description": "User-Customizable Theme System\n"}, {"description": "Create a Debug API Button that opens a modal showing the API response in text/JSON and a table\n"}, {"description": "Comprehensive error recovery strategy with rollback procedures\n"}, {"description": "Data migration system with schema versioning\n"}, {"description": "Agent coordination recovery mechanisms\n"}, {"description": "Automated performance regression testing\n"}, {"description": "Real-time collaboration features for agents\n"}, {"description": "Predictive failure detection system\n"}, {"description": "Advanced dependency resolution for agent tasks\n"}, {"description": "User experience metrics collection\n"}, {"description": "Automated CI/CD pipeline integration\n"}, {"description": "Data schema versioning system implementation\n"}, {"description": "localStorage corruption detection utilities\n"}, {"description": "Automated migration scripts for breaking changes\n"}, {"description": "Performance baseline and monitoring infrastructure\n"}, {"description": "Security threat model documentation\n"}, {"description": "Dependency vulnerability tracking system\n"}, {"description": "Agent task coordination database\n"}, {"description": "Distributed task management system\n"}, {"description": "Emergency procedures documentation (`/docs/emergency-procedures.md`)\n"}, {"description": "Advanced agent handoff validation system\n"}, {"description": "Integration test suite for core workflows\n"}, {"description": "Cross-theme compatibility verification automation\n"}, {"description": "Regression testing pipeline for major changes\n"}, {"description": "Agent coordination failure simulation\n"}, {"description": "XSS/injection attack simulation testing\n"}, {"description": "Browser compatibility automation\n"}, {"description": "Performance benchmark automation\n"}, {"description": "Data integrity validation during upgrades\n"}, {"description": "Performance Optimization Quick Wins (100 min total)\n"}, {"description": "Fix bug in user authentication module\n"}, {"description": "Add unit tests for payment gateway\n"}, {"description": "Update API documentation for v2.0\n"}]